django_grpc/__init__.py
django_grpc/apps.py
django_grpc/helpers/__init__.py
django_grpc/helpers/ratelimit.py
django_grpc/management/__init__.py
django_grpc/management/commands/grpcserver.py
django_grpc/models.py
django_grpc/serializers/__init__.py
django_grpc/serializers/base.py
django_grpc/signals/__init__.py
django_grpc/signals/wrapper.py
django_grpc/utils.py
django_grpc_testtools/__init__.py
django_grpc_testtools/context.py
django_grpc_testtools/executor.py
django_grpc-1.1.2.dist-info/AUTHORS.md
django_grpc-1.1.2.dist-info/LICENSE
django_grpc-1.1.2.dist-info/METADATA
django_grpc-1.1.2.dist-info/WHEEL
django_grpc-1.1.2.dist-info/RECORD
