Metadata-Version: 2.3
Name: django-grpc
Version: 1.1.2
Summary: Easy gRPC service based on Django application
License: MIT
Author: Stan Misiurev
Author-email: smisiurev@gmail.com
Requires-Python: >=3.11,<4.0
Classifier: License :: OSI Approved :: MIT License
Classifier: Programming Language :: Python :: 3
Classifier: Programming Language :: Python :: 3.11
Classifier: Programming Language :: Python :: 3.12
Classifier: Programming Language :: Python :: 3.13
Requires-Dist: django (>=4.2,<6.0)
Requires-Dist: grpcio
Requires-Dist: grpcio-reflection
Requires-Dist: grpcio-tools
Requires-Dist: protobuf
